Metadata-Version: 2.1
Name: nn-without-frameworks
Version: 0.1.3
Summary: Building Neural Networks from scratch.
Home-page: https://github.com/alirezakazemipour/NN-Without-Frameworks
Author: Alireza Kazemipour
Author-email: kazemipour.alireza@gmail.com
License: UNKNOWN
Platform: UNKNOWN
Classifier: Programming Language :: Python :: 3
Classifier: License :: OSI Approved :: MIT License
Classifier: Operating System :: OS Independent
Requires-Python: >=3.6
License-File: LICENSE
Requires-Dist: tabulate
Requires-Dist: numpy
